DummyGenerator/DummyGenerator.py
DummyGenerator/__init__.py
DummyGenerator/models/age_net.caffemodel
DummyGenerator/models/deploy.prototxt.txt
DummyGenerator/models/deploy_age.prototxt
DummyGenerator/models/deploy_gender.prototxt
DummyGenerator/models/gender_net.caffemodel
DummyGenerator/models/res10_300x300_ssd_iter_140000_fp16.caffemodel
DummyGenerator-1.0.0.dist-info/LICENSE
DummyGenerator-1.0.0.dist-info/METADATA
DummyGenerator-1.0.0.dist-info/WHEEL
DummyGenerator-1.0.0.dist-info/top_level.txt
DummyGenerator-1.0.0.dist-info/RECORD
