Metadata-Version: 2.1
Name: DummyGenerator
Version: 1.0.0
Summary: Create dummy people for testing
Author-email: Parick Sørensen <patricklykke@live.dk>
Classifier: Programming Language :: Python :: 3
Classifier: License :: OSI Approved :: MIT License
Classifier: Operating System :: OS Independent
Requires-Python: >=3.7
License-File: LICENSE
